music/__init__.py
music/py.typed
music/cli/__init__.py
music/cli/entry_point.py
music/cli/webapp.py
music/clients/__init__.py
music/clients/_spotify.py
music/clients/spotdl.py
music/clients/spotify.py
music/clients/utils.py
music/context/__init__.py
music/context/config.py
music/context/context_.py
music/context/options.py
music/context/secrets_.py
music/download/__init__.py
music/download/download_new_songs.py
music/download/downloaded_songs_processor.py
music/download/downloader.py
music/download/spotdl.py
music/main/__init__.py
music/main/_main.py
music/main/uploader.py
music/models/__init__.py
music/models/artist.py
music/models/path.py
music/models/response_types.py
music/models/youtube.py
music/runtime/__init__.py
music/runtime/runtime.py
music/server/__init__.py
music/server/app.py
music/server/routers/__init__.py
music/server/routers/artists.py
music/server/routers/songs.py
music/server/servers/__init__.py
music/server/servers/artists.py
music/server/servers/songs.py
music/storage/__init__.py
music/storage/artist.py
music/storage/artist_paths.py
music/storage/storage.py
music/updaters/__init__.py
music/updaters/artist.py
music/updaters/artists.py
music/updaters/download_ids.py
music/utils/__init__.py
music/utils/batched.py
music/utils/ci_context.py
music/utils/progress.py
musicmaster-1.4.4.dist-info/licenses/LICENSE
musicmaster-1.4.4.dist-info/METADATA
musicmaster-1.4.4.dist-info/WHEEL
musicmaster-1.4.4.dist-info/entry_points.txt
musicmaster-1.4.4.dist-info/top_level.txt
musicmaster-1.4.4.dist-info/RECORD
