Metadata-Version: 2.4
Name: musicmaster
Version: 1.4.4
Summary: Analyze your favorite music
Author-email: Quinten Roets <qdr2104@columbia.edu>
License-Expression: MIT
Project-URL: Source Code, https://github.com/quintenroets/music
Requires-Python: <3.14,>=3.10
License-File: LICENSE
Requires-Dist: dirhash<1,>=0.2.1
Requires-Dist: fastapi<1,>=0.103.2
Requires-Dist: hostfinder<2,>=1.0.1
Requires-Dist: mutagen<2,>=1.47.0
Requires-Dist: package-utils[context]<1,>=0.6.3
Requires-Dist: powercli<1,>=0.2.0
Requires-Dist: powertrace<1,>=0.1.1
Requires-Dist: pysftp<1,>=0.2.9
Requires-Dist: retry<1,>=0.9.2
Requires-Dist: spotipy<3,>=2.23.0
Requires-Dist: spotdl<5,>=4.2.4
Requires-Dist: superpathlib<3,>=2.0.6
Requires-Dist: webapp-starter<1,>=0.1.4
Provides-Extra: dev
Requires-Dist: hypothesis<7,>=6.91.0; extra == "dev"
Requires-Dist: httpx<0.28,>=0.26.0; extra == "dev"
Requires-Dist: package-dev-tools<1,>=0.7.1; extra == "dev"
Requires-Dist: package-dev-utils<1,>=0.1.6; extra == "dev"
Requires-Dist: types-pysftp<1,>=0.2.17.6; extra == "dev"
Requires-Dist: types-requests<3,>=2.31.0.10; extra == "dev"
Requires-Dist: types-retry<1,>=0.9.9.4; extra == "dev"
Provides-Extra: ci
Requires-Dist: backupmaster<3,>=2.0.3; extra == "ci"
Dynamic: license-file
